eks_best_practices_cli/__init__.py
eks_best_practices_cli/helpers.py
eks_best_practices_cli/main.py
eks_best_practices_cli/report/__init__.py
eks_best_practices_cli/report/print.py
eks_best_practices_cli/security/__init__.py
eks_best_practices_cli/security/auditing_logging/__init__.py
eks_best_practices_cli/security/auditing_logging/rules.py
eks_best_practices_cli/security/iam/__init__.py
eks_best_practices_cli/security/iam/rules.py
eks_best_practices_cli/security/multi_tenancy/__init__.py
eks_best_practices_cli/security/multi_tenancy/rules.py
eks_best_practices_cli/security/network_security/__init__.py
eks_best_practices_cli/security/network_security/rules.py
eks_best_practices_cli/security/pod_security/__init__.py
eks_best_practices_cli/security/pod_security/rules.py
eks_best_practices_cli-0.1.1.dist-info/entry_points.txt
eks_best_practices_cli-0.1.1.dist-info/LICENSE
eks_best_practices_cli-0.1.1.dist-info/WHEEL
eks_best_practices_cli-0.1.1.dist-info/METADATA
eks_best_practices_cli-0.1.1.dist-info/RECORD
