Metadata-Version: 2.1
Name: eks-best-practices-cli
Version: 0.1.1
Summary: 
Author: Doruk Ozturk
Author-email: dozturk@amazon.com
Requires-Python: >=3.9,<4.0
Classifier: Programming Language :: Python :: 3
Classifier: Programming Language :: Python :: 3.9
Classifier: Programming Language :: Python :: 3.10
Requires-Dist: boto3 (>=1.24.63,<2.0.0)
Requires-Dist: kubernetes (>=24.2.0,<25.0.0)
Requires-Dist: rich (>=12.5.1,<13.0.0)
Requires-Dist: typer-cli (>=0.0.12,<0.0.13)
